MANIFEST.in
README.md
iFinDPy.py
setup.py
iFinDAPI/VERSION.txt
iFinDAPI/__init__.py
iFinDAPI.egg-info/PKG-INFO
iFinDAPI.egg-info/SOURCES.txt
iFinDAPI.egg-info/dependency_links.txt
iFinDAPI.egg-info/requires.txt
iFinDAPI.egg-info/top_level.txt
iFinDAPI/Linux/__init__.py
iFinDAPI/Linux/bin64/__init__.py
iFinDAPI/Linux/bin64/libFTDataInterface.so
iFinDAPI/Linux/bin64/libShellExport.so
iFinDAPI/Linux/bin64/libhcrypt-3.1.so
iFinDAPI/Linux/bin64/Tool/__init__.py
iFinDAPI/Linux/bin64/Tool/etc/__init__.py
iFinDAPI/Linux/bin64/Tool/etc/system_setting.ini
iFinDAPI/Linux/bin64/etc/UpdatFileInfo.xml
iFinDAPI/Linux/bin64/etc/XlsThsFunc.xml
iFinDAPI/Linux/bin64/etc/__init__.py
iFinDAPI/Linux/bin64/etc/config.ini
iFinDAPI/Linux/bin64/etc/domainnamemgr.xml
iFinDAPI/Linux/bin64/etc/new_serverinfo.xml
iFinDAPI/Linux/bin64/etc/stock_linkage.xml
iFinDAPI/Linux/bin64/etc/system_native.ini
iFinDAPI/Linux/bin64/etc/datacube/ErrorInfor.xml
iFinDAPI/Linux/bin64/etc/datacube/NewDataPool.xml
iFinDAPI/Linux/bin64/etc/datacube/XlsBlock.xml
iFinDAPI/Linux/bin64/etc/datacube/XlsMVIndis.xml
iFinDAPI/Linux/bin64/etc/datacube/__init__.py
iFinDAPI/Linux/bin64/etc/datacube/excel.xml
iFinDAPI/Linux/bin64/etc/datacube/params.xml
iFinDAPI/Linux/bin64/etc/hqplug/__init__.py
iFinDAPI/Linux/bin64/etc/hqplug/config.ini
iFinDAPI/Windows/__init__.py
iFinDAPI/Windows/bin/__init__.py
iFinDAPI/Windows/bin/Tool/__init__.py
iFinDAPI/Windows/bin/Tool/iDataLP.exe
iFinDAPI/Windows/bin/Tool/etc/__init__.py
iFinDAPI/Windows/bin/Tool/etc/system_setting.ini
iFinDAPI/Windows/bin/x64/FTDataInterface_x64.dll
iFinDAPI/Windows/bin/x64/FTlibcurl_x64.dll
iFinDAPI/Windows/bin/x64/IEShims.dll
iFinDAPI/Windows/bin/x64/Microsoft.VC90.ATL.manifest
iFinDAPI/Windows/bin/x64/Microsoft.VC90.CRT.manifest
iFinDAPI/Windows/bin/x64/Microsoft.VC90.MFC.manifest
iFinDAPI/Windows/bin/x64/ShellExport.dll
iFinDAPI/Windows/bin/x64/__init__.py
iFinDAPI/Windows/bin/x64/baratol_dll_r_x64.dll
iFinDAPI/Windows/bin/x64/device_fingerprint.dll
iFinDAPI/Windows/bin/x64/gpsvc.dll
iFinDAPI/Windows/bin/x64/hcrypt_x64.dll
iFinDAPI/Windows/bin/x64/libbz2.dll
iFinDAPI/Windows/bin/x64/libcurl_x64.dll
