Metadata-Version: 2.1
Name: iFinDAPI
Version: 0.0.7
Summary: THS_DataInterface SDK API
Home-page: https://quantapi.51ifind.com/
Author: ifind
Author-email: ifind_webexcel@myhexin.com
License: Apache License v2
Keywords: iFinDAPI,datainterface,FTDI,iFinDSDK,thsAPI
Classifier: Programming Language :: Python :: 3
Classifier: Operating System :: Microsoft :: Windows
Classifier: Operating System :: Unix
Requires-Python: >=3.7
